pretix_hobex/__init__.py
pretix_hobex/apps.py
pretix_hobex/payment.py
pretix_hobex/paymentmethods.py
pretix_hobex/signals.py
pretix_hobex/urls.py
pretix_hobex/locale/django.pot
pretix_hobex/locale/de/LC_MESSAGES/django.mo
pretix_hobex/locale/de/LC_MESSAGES/django.po
pretix_hobex/locale/de_Informal/LC_MESSAGES/django.mo
pretix_hobex/locale/de_Informal/LC_MESSAGES/django.po
pretix_hobex/static/pretix_hobex/logo.png
pretix_hobex/static/pretix_hobex/paybybank_hobex.png
pretix_hobex/static/pretix_hobex/pretix-hobex.scss
pretix_hobex/templates/pretix_hobex/.gitkeep
pretix_hobex/templates/pretix_hobex/pay_head.html
pretix_oppwa/__init__.py
pretix_oppwa/apps.py
pretix_oppwa/payment.py
pretix_oppwa/paymentmethods.py
pretix_oppwa/signals.py
pretix_oppwa/urls.py
pretix_oppwa/views.py
pretix_oppwa/locale/django.pot
pretix_oppwa/locale/de/LC_MESSAGES/django.mo
pretix_oppwa/locale/de/LC_MESSAGES/django.po
pretix_oppwa/locale/de_Informal/.gitkeep
pretix_oppwa/locale/de_Informal/LC_MESSAGES/django.mo
pretix_oppwa/locale/de_Informal/LC_MESSAGES/django.po
pretix_oppwa/static/pretix_oppwa/.gitkeep
pretix_oppwa/static/pretix_oppwa/pretix-oppwa.css
pretix_oppwa/static/pretix_oppwa/pretix-oppwa.js
pretix_oppwa/templates/pretix_oppwa/.gitkeep
pretix_oppwa/templates/pretix_oppwa/checkout_payment_confirm.html
pretix_oppwa/templates/pretix_oppwa/checkout_payment_form.html
pretix_oppwa/templates/pretix_oppwa/control.html
pretix_oppwa/templates/pretix_oppwa/pay.html
pretix_oppwa/templates/pretix_oppwa/pending.html
pretix_oppwa/templates/pretix_oppwa/redirect.html
pretix_oppwa-1.4.0.dist-info/licenses/LICENSE
pretix_vrpay/__init__.py
pretix_vrpay/apps.py
pretix_vrpay/payment.py
pretix_vrpay/paymentmethods.py
pretix_vrpay/signals.py
pretix_vrpay/urls.py
pretix_vrpay/locale/django.pot
pretix_vrpay/locale/de/LC_MESSAGES/django.mo
pretix_vrpay/locale/de/LC_MESSAGES/django.po
pretix_vrpay/locale/de_Informal/LC_MESSAGES/django.mo
pretix_vrpay/locale/de_Informal/LC_MESSAGES/django.po
pretix_vrpay/static/pretix_vrpay/logo.svg
pretix_oppwa-1.4.0.dist-info/METADATA
pretix_oppwa-1.4.0.dist-info/WHEEL
pretix_oppwa-1.4.0.dist-info/entry_points.txt
pretix_oppwa-1.4.0.dist-info/top_level.txt
pretix_oppwa-1.4.0.dist-info/RECORD
