Metadata-Version: 2.4
Name: pretix-oppwa
Version: 1.4.0
Summary: This plugin allows you to use OPPWA based payment providers
Author-email: pretix team <support@pretix.eu>
Maintainer-email: pretix team <support@pretix.eu>
License: 
Project-URL: homepage, https://github.com/pretix/pretix-oppwa/
Keywords: pretix
Requires-Python: >=3.9
License-File: LICENSE
Dynamic: license-file
